setup.py
dork_compose/__init__.py
dork_compose/helpers.py
dork_compose/injections.py
dork_compose/main.py
dork_compose/plugin.py
dork_compose.egg-info/PKG-INFO
dork_compose.egg-info/SOURCES.txt
dork_compose.egg-info/dependency_links.txt
dork_compose.egg-info/entry_points.txt
dork_compose.egg-info/requires.txt
dork_compose.egg-info/top_level.txt
dork_compose/auxiliary/dns/docker-compose.yml
dork_compose/auxiliary/proxy/dockergen/Dockerfile
dork_compose/auxiliary/proxy/dockergen/nginx.tmpl
dork_compose/auxiliary/proxy/letsencrypt/docker-compose.yml
dork_compose/auxiliary/proxy/nginx/Dockerfile
dork_compose/auxiliary/proxy/nginx/nginx.conf
dork_compose/auxiliary/proxy/none/docker-compose.yml
dork_compose/auxiliary/proxy/selfsigned/docker-compose.yml
dork_compose/auxiliary/vault/docker-compose.yml
dork_compose/plugins/autobuild.py
dork_compose/plugins/cleanup.py
dork_compose/plugins/dns.py
dork_compose/plugins/env.py
dork_compose/plugins/filesystem.py
dork_compose/plugins/git.py
dork_compose/plugins/hotcode.py
dork_compose/plugins/lib.py
dork_compose/plugins/multi.py
dork_compose/plugins/proxy.py
dork_compose/plugins/single.py
dork_compose/plugins/subnet.py
dork_compose/plugins/tracker.py
dork_compose/plugins/tree.py
dork_compose/plugins/vault.py