Metadata-Version: 1.1
Name: dork-compose
Version: 1.13.0.0.0.1
Summary: docker-compose with magicks.
Home-page: https://github.com/iamdork/dork
Author: Philipp Melab
Author-email: philipp.melab@gmail.com
License: MIT
Keywords: docker docker-compose devops development
Platform: UNKNOWN
Classifier: Development Status :: 3 - Alpha
Classifier: Intended Audience :: Developers
Classifier: Topic :: Software Development :: Build Tools
Classifier: License :: OSI Approved :: MIT License
Classifier: Programming Language :: Python :: 2.6
Classifier: Programming Language :: Python :: 2.7
